nautobot_deepcopy/__init__.py
nautobot_deepcopy/forms.py
nautobot_deepcopy/template_content.py
nautobot_deepcopy/templates/nautobot_deepcopy/copy.html
nautobot_deepcopy/templates/nautobot_deepcopy/inc/buttons.html
nautobot_deepcopy/urls.py
nautobot_deepcopy/views.py
nautobot_deepcopy-1.0.3.dist-info/METADATA
nautobot_deepcopy-1.0.3.dist-info/WHEEL
nautobot_deepcopy-1.0.3.dist-info/RECORD
