Metadata-Version: 2.3
Name: nautobot-deepcopy
Version: 1.0.3
Summary: Nautobot Plugin to copy a device with all its components
Author: Gesellschaft für wissenschaftliche Datenverarbeitung mbH Göttingen
Author-email: netzadmin@gwdg.de
Requires-Python: >=3.8,<3.12
Classifier: Programming Language :: Python :: 3
Classifier: Programming Language :: Python :: 3.8
Classifier: Programming Language :: Python :: 3.9
Classifier: Programming Language :: Python :: 3.10
Classifier: Programming Language :: Python :: 3.11
Requires-Dist: nautobot (>=2)
